README.md
setup.cfg
setup.py
simublocks/__init__.py
simublocks/simublocks.py
simublocks.egg-info/PKG-INFO
simublocks.egg-info/SOURCES.txt
simublocks.egg-info/dependency_links.txt
simublocks.egg-info/entry_points.txt
simublocks.egg-info/requires.txt
simublocks.egg-info/top_level.txt
simublocks/dialog/__init__.py
simublocks/dialog/alertDialog.py
simublocks/dialog/dialogTools.py
simublocks/dialog/editBlockDialog.py
simublocks/dialog/editGraphDialog.py
simublocks/dialog/executeDialog.py
simublocks/dialog/importCodeDialog.py
simublocks/dialog/newBlockDialog.py
simublocks/dialog/newCornerDialog.py
simublocks/element/__init__.py
simublocks/element/connection.py
simublocks/element/block/__init__.py
simublocks/element/block/block.py
simublocks/element/block/corner.py
simublocks/element/block/graph.py
simublocks/element/block/input.py
simublocks/element/block/sum.py
simublocks/element/block/system.py
simublocks/element/block/tools.py
simublocks/examples/__init__.py
simublocks/examples/closedloop.py
simublocks/examples/noise.py
simublocks/examples/openloop.py
simublocks/menubar/__init__.py
simublocks/menubar/file.py
simublocks/menubar/simulation.py
simublocks/simulation/__init__.py
simublocks/simulation/plot.py
simublocks/simulation/self.py
simublocks/simulation/tools.py