Metadata-Version: 2.1
Name: simublocks
Version: 1.1.8
Summary: Python Simulation Blocks for Dynamic Systems
Home-page: https://github.com/bentoavb/simublocks
Author: Anderson Vitor Bento
Author-email: bentoavb@gmail.com
License: UNKNOWN
Platform: UNKNOWN
Classifier: Programming Language :: Python :: 3
Classifier: License :: OSI Approved :: MIT License
Classifier: Operating System :: OS Independent
